vvv_rpc/__init__.py
vvv_rpc/v_jshook_extension.zip
vvv_rpc/websocket/__init__.py
vvv_rpc/websocket/_abnf.py
vvv_rpc/websocket/_app.py
vvv_rpc/websocket/_cookiejar.py
vvv_rpc/websocket/_core.py
vvv_rpc/websocket/_exceptions.py
vvv_rpc/websocket/_handshake.py
vvv_rpc/websocket/_http.py
vvv_rpc/websocket/_logging.py
vvv_rpc/websocket/_socket.py
vvv_rpc/websocket/_ssl_compat.py
vvv_rpc/websocket/_url.py
vvv_rpc/websocket/_utils.py
vvv_rpc/websocket/_wsdump.py
vvv_rpc-0.1.26.dist-info/METADATA
vvv_rpc-0.1.26.dist-info/WHEEL
vvv_rpc-0.1.26.dist-info/entry_points.txt
vvv_rpc-0.1.26.dist-info/top_level.txt
vvv_rpc-0.1.26.dist-info/RECORD
