Metadata-Version: 2.1
Name: vvv-rpc
Version: 0.1.26
Summary: vvv_rpc.
Author: vilame
Author-email: opaquism@hotmail.com
License: MIT
Keywords: vvv_rpc
Classifier: License :: OSI Approved :: MIT License
Classifier: Programming Language :: Python
Classifier: Intended Audience :: Developers
Requires-Python: >=3.5
Requires-Dist: requests
